csv2ies/__init__.py
csv2ies/__main__.py
csv2ies/csv2ies.py
csv2ies-1.0.3.dist-info/LICENSE
csv2ies-1.0.3.dist-info/METADATA
csv2ies-1.0.3.dist-info/WHEEL
csv2ies-1.0.3.dist-info/entry_points.txt
csv2ies-1.0.3.dist-info/top_level.txt
csv2ies-1.0.3.dist-info/RECORD
