Metadata-Version: 2.1
Name: csv2ies
Version: 1.0.3
Summary: Import users from a CSV file into IES
Author-email: Jan Arman Parpin <parpin@sitepark.com>
Project-URL: Homepage, https://gitlab.sitepark.com/internal/csv2ies
Project-URL: Bug Tracker, https://gitlab.sitepark.com/internal/csv2ies/-/issues
Classifier: Programming Language :: Python :: 3
Classifier: License :: OSI Approved :: MIT License
Classifier: Operating System :: POSIX :: Linux
Classifier: Operating System :: Microsoft :: Windows
Requires-Python: >=3.10
License-File: LICENSE
Requires-Dist: requests
